dlib_installer/__init__.py
dlib_installer-0.1.dist-info/LICENSE
dlib_installer-0.1.dist-info/METADATA
dlib_installer-0.1.dist-info/WHEEL
dlib_installer-0.1.dist-info/top_level.txt
dlib_installer-0.1.dist-info/RECORD
