Metadata-Version: 2.1
Name: dlib-installer
Version: 0.1
Summary: A package to install the correct version of dlib on Windows.
Home-page: https://github.com/yourusername/dlib_installer
Author: Ibrahim Aloui
Author-email: ibrahimaloui433@gmail.com
Classifier: Programming Language :: Python :: 3
Classifier: Operating System :: Microsoft :: Windows
License-File: LICENSE
